dnsresolv/__init__.py
dnsresolv/main.py
dnsresolv/version.py
dnsresolv-0.0.4.dist-info/LICENSE
dnsresolv-0.0.4.dist-info/METADATA
dnsresolv-0.0.4.dist-info/WHEEL
dnsresolv-0.0.4.dist-info/entry_points.txt
dnsresolv-0.0.4.dist-info/top_level.txt
dnsresolv-0.0.4.dist-info/RECORD
